odoo9_addon_web_m2x_options-9.0.1.1.0-py2.7-nspkg.pth
odoo_addons/web_m2x_options/__openerp__.py
odoo_addons/web_m2x_options/__init__.py
odoo_addons/web_m2x_options/README.rst
odoo_addons/web_m2x_options/i18n/it.po
odoo_addons/web_m2x_options/i18n/es.po
odoo_addons/web_m2x_options/i18n/ar.po
odoo_addons/web_m2x_options/i18n/tr.po
odoo_addons/web_m2x_options/i18n/hr.po
odoo_addons/web_m2x_options/i18n/sl.po
odoo_addons/web_m2x_options/i18n/de.po
odoo_addons/web_m2x_options/i18n/fr.po
odoo_addons/web_m2x_options/i18n/pt_BR.po
odoo_addons/web_m2x_options/i18n/fi.po
odoo_addons/web_m2x_options/views/view.xml
odoo_addons/web_m2x_options/static/description/index.html
odoo_addons/web_m2x_options/static/description/icon.png
odoo_addons/web_m2x_options/static/src/js/form.js
odoo_addons/web_m2x_options/static/src/xml/base.xml
odoo9_addon_web_m2x_options-9.0.1.1.0.dist-info/top_level.txt
odoo9_addon_web_m2x_options-9.0.1.1.0.dist-info/WHEEL
odoo9_addon_web_m2x_options-9.0.1.1.0.dist-info/RECORD
odoo9_addon_web_m2x_options-9.0.1.1.0.dist-info/metadata.json
odoo9_addon_web_m2x_options-9.0.1.1.0.dist-info/DESCRIPTION.rst
odoo9_addon_web_m2x_options-9.0.1.1.0.dist-info/METADATA
odoo9_addon_web_m2x_options-9.0.1.1.0.dist-info/namespace_packages.txt
