Metadata-Version: 2.0
Name: odoo9-addon-web-m2x-options
Version: 9.0.1.1.0
Summary: web_m2x_options
Home-page: UNKNOWN
Author: ACSONE SA/NV, 0k.io, Tecnativa, Odoo Community Association (OCA)
Author-email: support@odoo-community.org
License: AGPL-3
Platform: UNKNOWN
Requires-Dist: odoo (<9.1a,>=9.0a)
Classifier: Programming Language :: Python :: 2.7
Classifier: Framework :: Odoo
Classifier: License :: OSI Approved :: GNU Affero General Public License v3
